<?xml version="1.0" encoding="UTF-8"?><wls:weblogic-web-app xmlns:wls="http://xmlns.oracle.com/weblogic/weblogic-web-app" xmlns:xsi="http://www.w3.org/2001/XMLSchema-instance" xsi:schemaLocation="http://java.sun.com/xml/ns/javaee http://java.sun.com/xml/ns/javaee/web-app_3_0.xsd http://xmlns.oracle.com/weblogic/weblogic-web-app http://xmlns.oracle.com/weblogic/weblogic-web-app/1.7/weblogic-web-app.xsd">    <wls:weblogic-version>12.1.3</wls:weblogic-version>        <wls:session-descriptor>		<wls:timeout-secs>1800</wls:timeout-secs>		<wls:cookie-name>JSESSIONID</wls:cookie-name>		<wls:cookie-http-only>true</wls:cookie-http-only>	</wls:session-descriptor>	<wls:container-descriptor>		<wls:servlet-reload-check-secs>-1</wls:servlet-reload-check-secs>		<wls:resource-reload-check-secs>-1</wls:resource-reload-check-secs>	</wls:container-descriptor></wls:weblogic-web-app>